{
  "author": "Sky Ao <aoxiaojian@gmail.cn>",
  "description": "gRPC学习笔记",
  "extension": null,
  "generator": "site",
  "sidebar": {
    "Sky@gitbook": "https://skyao.gitbooks.io"
  },
  "output": null,
  "pdf": {
    "fontSize": 12,
    "footerTemplate": null,
    "headerTemplate": null,
    "margin": {
      "bottom": 36,
      "left": 62,
      "right": 62,
      "top": 36
    },
    "pageNumbers": false,
    "paperSize": "a4"
  },
  "plugins": [],
  "title": "gRPC学习笔记",
  "variables": {
  }
}
